psgyolo/LICENSE.txt
psgyolo/README.md
psgyolo/__init__.py
psgyolo/__main__.py
psgyolo/psgyolo.py
psgyolo/screenshot.jpg
psgyolo/screenshot2.gif
psgyolo/yolo-coco/coco.names
psgyolo/yolo-coco/yolov3.cfg
psgyolo/yolo-coco/yolov3.weights README
psgyolo-5.0.0.dist-info/LICENSE.txt
psgyolo-5.0.0.dist-info/METADATA
psgyolo-5.0.0.dist-info/WHEEL
psgyolo-5.0.0.dist-info/entry_points.txt
psgyolo-5.0.0.dist-info/top_level.txt
psgyolo-5.0.0.dist-info/RECORD
